{
  "info": {
    "_postman_id": "slimedoesgamez-api-collection",
    "name": "SlimeDoesGamez API Collection",
    "description": "Complete API collection for SlimeDoesGamez Backend - Customer Registration with OTP Verification",
    "schema": "https://schema.getpostman.com/json/collection/v2.1.0/collection.json",
    "_exporter_id": "12345678"
  },
  "item": [
    {
      "name": "Auth",
      "description": "Authentication endpoints for customer registration and OTP verification",
      "item": [
        {
          "name": "Register Customer",
          "request": {
            "method": "POST",
            "header": [
              {
                "key": "Content-Type",
                "value": "application/json",
                "type": "text"
              }
            ],
            "body": {
              "mode": "raw",
              "raw": "{\n  \"email\": \"john@example.com\",\n  \"password\": \"SecurePassword123\",\n  \"firstName\": \"John\",\n  \"lastName\": \"Doe\",\n  \"phone\": \"+1234567890\"\n}"
            },
            "url": {
              "raw": "{{base_url}}/api/users/auth/register",
              "host": [
                "{{base_url}}"
              ],
              "path": [
                "api",
                "users",
                "auth",
                "register"
              ]
            },
            "description": "Register a new customer account. Sends OTP to email for verification."
          },
          "response": [
            {
              "name": "Success Response (201)",
              "originalRequest": {
                "method": "POST",
                "header": [
                  {
                    "key": "Content-Type",
                    "value": "application/json",
                    "type": "text"
                  }
                ],
                "body": {
                  "mode": "raw",
                  "raw": "{\n  \"email\": \"john@example.com\",\n  \"password\": \"SecurePassword123\",\n  \"firstName\": \"John\",\n  \"lastName\": \"Doe\",\n  \"phone\": \"+1234567890\"\n}"
                },
                "url": {
                  "raw": "{{base_url}}/api/users/auth/register",
                  "host": [
                    "{{base_url}}"
                  ],
                  "path": [
                    "api",
                    "users",
                    "auth",
                    "register"
                  ]
                }
              },
              "status": "Created",
              "code": 201,
              "header": [
                {
                  "key": "Content-Type",
                  "value": "application/json"
                }
              ],
              "body": "{\n  \"success\": true,\n  \"message\": \"Registration successful! OTP sent to your email.\",\n  \"data\": {\n    \"email\": \"john@example.com\",\n    \"firstName\": \"John\"\n  }\n}"
            },
            {
              "name": "Error - Missing Fields (400)",
              "originalRequest": {
                "method": "POST",
                "header": [
                  {
                    "key": "Content-Type",
                    "value": "application/json",
                    "type": "text"
                  }
                ],
                "body": {
                  "mode": "raw",
                  "raw": "{\n  \"email\": \"john@example.com\"\n}"
                },
                "url": {
                  "raw": "{{base_url}}/api/users/auth/register",
                  "host": [
                    "{{base_url}}"
                  ],
                  "path": [
                    "api",
                    "users",
                    "auth",
                    "register"
                  ]
                }
              },
              "status": "Bad Request",
              "code": 400,
              "header": [
                {
                  "key": "Content-Type",
                  "value": "application/json"
                }
              ],
              "body": "{\n  \"success\": false,\n  \"error\": \"Email, password, and first name are required\"\n}"
            }
          ]
        },
        {
          "name": "Verify OTP",
          "request": {
            "method": "POST",
            "header": [
              {
                "key": "Content-Type",
                "value": "application/json",
                "type": "text"
              }
            ],
            "body": {
              "mode": "raw",
              "raw": "{\n  \"email\": \"john@example.com\",\n  \"otp\": \"12345\"\n}"
            },
            "url": {
              "raw": "{{base_url}}/api/users/auth/verify-otp",
              "host": [
                "{{base_url}}"
              ],
              "path": [
                "api",
                "users",
                "auth",
                "verify-otp"
              ]
            },
            "description": "Verify the 5-digit OTP sent to customer's email. Marks email as verified upon success."
          },
          "response": [
            {
              "name": "Success Response (200)",
              "originalRequest": {
                "method": "POST",
                "header": [
                  {
                    "key": "Content-Type",
                    "value": "application/json",
                    "type": "text"
                  }
                ],
                "body": {
                  "mode": "raw",
                  "raw": "{\n  \"email\": \"john@example.com\",\n  \"otp\": \"12345\"\n}"
                },
                "url": {
                  "raw": "{{base_url}}/api/users/auth/verify-otp",
                  "host": [
                    "{{base_url}}"
                  ],
                  "path": [
                    "api",
                    "users",
                    "auth",
                    "verify-otp"
                  ]
                }
              },
              "status": "OK",
              "code": 200,
              "header": [
                {
                  "key": "Content-Type",
                  "value": "application/json"
                }
              ],
              "body": "{\n  \"success\": true,\n  \"message\": \"Email verified successfully!\",\n  \"data\": {\n    \"email\": \"john@example.com\",\n    \"userId\": \"550e8400-e29b-41d4-a716-446655440000\"\n  }\n}"
            },
            {
              "name": "Error - Expired OTP (400)",
              "originalRequest": {
                "method": "POST",
                "header": [
                  {
                    "key": "Content-Type",
                    "value": "application/json",
                    "type": "text"
                  }
                ],
                "body": {
                  "mode": "raw",
                  "raw": "{\n  \"email\": \"john@example.com\",\n  \"otp\": \"12345\"\n}"
                },
                "url": {
                  "raw": "{{base_url}}/api/users/auth/verify-otp",
                  "host": [
                    "{{base_url}}"
                  ],
                  "path": [
                    "api",
                    "users",
                    "auth",
                    "verify-otp"
                  ]
                }
              },
              "status": "Bad Request",
              "code": 400,
              "header": [
                {
                  "key": "Content-Type",
                  "value": "application/json"
                }
              ],
              "body": "{\n  \"success\": false,\n  \"error\": \"OTP has expired. Please request a new OTP.\"\n}"
            },
            {
              "name": "Error - Invalid OTP (400)",
              "originalRequest": {
                "method": "POST",
                "header": [
                  {
                    "key": "Content-Type",
                    "value": "application/json",
                    "type": "text"
                  }
                ],
                "body": {
                  "mode": "raw",
                  "raw": "{\n  \"email\": \"john@example.com\",\n  \"otp\": \"99999\"\n}"
                },
                "url": {
                  "raw": "{{base_url}}/api/users/auth/verify-otp",
                  "host": [
                    "{{base_url}}"
                  ],
                  "path": [
                    "api",
                    "users",
                    "auth",
                    "verify-otp"
                  ]
                }
              },
              "status": "Bad Request",
              "code": 400,
              "header": [
                {
                  "key": "Content-Type",
                  "value": "application/json"
                }
              ],
              "body": "{\n  \"success\": false,\n  \"error\": \"Invalid OTP. Please try again.\"\n}"
            },
            {
              "name": "Error - Too Many Attempts (429)",
              "originalRequest": {
                "method": "POST",
                "header": [
                  {
                    "key": "Content-Type",
                    "value": "application/json",
                    "type": "text"
                  }
                ],
                "body": {
                  "mode": "raw",
                  "raw": "{\n  \"email\": \"john@example.com\",\n  \"otp\": \"99999\"\n}"
                },
                "url": {
                  "raw": "{{base_url}}/api/users/auth/verify-otp",
                  "host": [
                    "{{base_url}}"
                  ],
                  "path": [
                    "api",
                    "users",
                    "auth",
                    "verify-otp"
                  ]
                }
              },
              "status": "Too Many Requests",
              "code": 429,
              "header": [
                {
                  "key": "Content-Type",
                  "value": "application/json"
                }
              ],
              "body": "{\n  \"success\": false,\n  \"error\": \"Maximum OTP attempts exceeded. Please request a new OTP.\"\n}"
            }
          ]
        },
        {
          "name": "Resend OTP",
          "request": {
            "method": "POST",
            "header": [
              {
                "key": "Content-Type",
                "value": "application/json",
                "type": "text"
              }
            ],
            "body": {
              "mode": "raw",
              "raw": "{\n  \"email\": \"john@example.com\"\n}"
            },
            "url": {
              "raw": "{{base_url}}/api/users/auth/resend-otp",
              "host": [
                "{{base_url}}"
              ],
              "path": [
                "api",
                "users",
                "auth",
                "resend-otp"
              ]
            },
            "description": "Resend a new OTP to the customer's email if the previous one expired or was lost."
          },
          "response": [
            {
              "name": "Success Response (200)",
              "originalRequest": {
                "method": "POST",
                "header": [
                  {
                    "key": "Content-Type",
                    "value": "application/json",
                    "type": "text"
                  }
                ],
                "body": {
                  "mode": "raw",
                  "raw": "{\n  \"email\": \"john@example.com\"\n}"
                },
                "url": {
                  "raw": "{{base_url}}/api/users/auth/resend-otp",
                  "host": [
                    "{{base_url}}"
                  ],
                  "path": [
                    "api",
                    "users",
                    "auth",
                    "resend-otp"
                  ]
                }
              },
              "status": "OK",
              "code": 200,
              "header": [
                {
                  "key": "Content-Type",
                  "value": "application/json"
                }
              ],
              "body": "{\n  \"success\": true,\n  \"message\": \"New OTP sent to your email.\",\n  \"data\": {\n    \"email\": \"john@example.com\"\n  }\n}"
            },
            {
              "name": "Error - Already Verified (400)",
              "originalRequest": {
                "method": "POST",
                "header": [
                  {
                    "key": "Content-Type",
                    "value": "application/json",
                    "type": "text"
                  }
                ],
                "body": {
                  "mode": "raw",
                  "raw": "{\n  \"email\": \"john@example.com\"\n}"
                },
                "url": {
                  "raw": "{{base_url}}/api/users/auth/resend-otp",
                  "host": [
                    "{{base_url}}"
                  ],
                  "path": [
                    "api",
                    "users",
                    "auth",
                    "resend-otp"
                  ]
                }
              },
              "status": "Bad Request",
              "code": 400,
              "header": [
                {
                  "key": "Content-Type",
                  "value": "application/json"
                }
              ],
              "body": "{\n  \"success\": false,\n  \"error\": \"Email is already verified\"\n}"
            }
          ]
        },
        {
          "name": "Login Customer/Admin",
          "request": {
            "method": "POST",
            "header": [
              {
                "key": "Content-Type",
                "value": "application/json",
                "type": "text"
              }
            ],
            "body": {
              "mode": "raw",
              "raw": "{\n  \"email\": \"john@example.com\",\n  \"password\": \"SecurePassword123\"\n}"
            },
            "url": {
              "raw": "{{base_url}}/api/users/auth/login",
              "host": [
                "{{base_url}}"
              ],
              "path": [
                "api",
                "users",
                "auth",
                "login"
              ]
            },
            "description": "Login with verified email and password. Returns JWT token for both CUSTOMER and ADMIN roles."
          },
          "response": [
            {
              "name": "Login Success - Customer (200)",
              "originalRequest": {
                "method": "POST",
                "header": [
                  {
                    "key": "Content-Type",
                    "value": "application/json",
                    "type": "text"
                  }
                ],
                "body": {
                  "mode": "raw",
                  "raw": "{\n  \"email\": \"john@example.com\",\n  \"password\": \"SecurePassword123\"\n}"
                },
                "url": {
                  "raw": "{{base_url}}/api/users/auth/login",
                  "host": [
                    "{{base_url}}"
                  ],
                  "path": [
                    "api",
                    "users",
                    "auth",
                    "login"
                  ]
                }
              },
              "status": "OK",
              "code": 200,
              "header": [
                {
                  "key": "Content-Type",
                  "value": "application/json"
                }
              ],
              "body": "{\n  \"success\": true,\n  \"message\": \"Login successful\",\n  \"data\": {\n    \"token\": \"eyJhbGciOiJIUzI1NiIsInR5cCI6IkpXVCJ9.eyJ1c2VySWQiOiJ1dWlkIiwiZW1haWwiOiJqb2huQGV4YW1wbGUuY29tIiwicm9sZSI6IkNVU1RPTUVSIiwiaWF0IjoxNzAwMDAwMDAwLCJleHAiOjE3MDA2MDQ4MDB9.SIGNATURE\",\n    \"user\": {\n      \"id\": \"550e8400-e29b-41d4-a716-446655440000\",\n      \"email\": \"john@example.com\",\n      \"firstName\": \"John\",\n      \"lastName\": \"Doe\",\n      \"phone\": \"+1234567890\",\n      \"role\": \"CUSTOMER\",\n      \"avatarUrl\": null,\n      \"isEmailVerified\": true,\n      \"createdAt\": \"2024-01-01T00:00:00.000Z\",\n      \"updatedAt\": \"2024-01-01T00:00:00.000Z\"\n    }\n  }\n}"
            },
            {
              "name": "Login Success - Admin (200)",
              "originalRequest": {
                "method": "POST",
                "header": [
                  {
                    "key": "Content-Type",
                    "value": "application/json",
                    "type": "text"
                  }
                ],
                "body": {
                  "mode": "raw",
                  "raw": "{\n  \"email\": \"admin@example.com\",\n  \"password\": \"AdminPassword123\"\n}"
                },
                "url": {
                  "raw": "{{base_url}}/api/users/auth/login",
                  "host": [
                    "{{base_url}}"
                  ],
                  "path": [
                    "api",
                    "users",
                    "auth",
                    "login"
                  ]
                }
              },
              "status": "OK",
              "code": 200,
              "header": [
                {
                  "key": "Content-Type",
                  "value": "application/json"
                }
              ],
              "body": "{\n  \"success\": true,\n  \"message\": \"Login successful\",\n  \"data\": {\n    \"token\": \"eyJhbGciOiJIUzI1NiIsInR5cCI6IkpXVCJ9.eyJ1c2VySWQiOiJ1dWlkIiwiZW1haWwiOiJhZG1pbkBleGFtcGxlLmNvbSIsInJvbGUiOiJBRE1JTiIsImlhdCI6MTcwMDAwMDAwMCwiZXhwIjoxNzAwNjA0ODAwfQ.SIGNATURE\",\n    \"user\": {\n      \"id\": \"admin-uuid-here\",\n      \"email\": \"admin@example.com\",\n      \"firstName\": \"Admin\",\n      \"lastName\": \"User\",\n      \"phone\": \"+1234567890\",\n      \"role\": \"ADMIN\",\n      \"avatarUrl\": null,\n      \"isEmailVerified\": true,\n      \"createdAt\": \"2024-01-01T00:00:00.000Z\",\n      \"updatedAt\": \"2024-01-01T00:00:00.000Z\"\n    }\n  }\n}"
            },
            {
              "name": "Error - Missing Fields (400)",
              "originalRequest": {
                "method": "POST",
                "header": [
                  {
                    "key": "Content-Type",
                    "value": "application/json",
                    "type": "text"
                  }
                ],
                "body": {
                  "mode": "raw",
                  "raw": "{\n  \"email\": \"john@example.com\"\n}"
                },
                "url": {
                  "raw": "{{base_url}}/api/users/auth/login",
                  "host": [
                    "{{base_url}}"
                  ],
                  "path": [
                    "api",
                    "users",
                    "auth",
                    "login"
                  ]
                }
              },
              "status": "Bad Request",
              "code": 400,
              "header": [
                {
                  "key": "Content-Type",
                  "value": "application/json"
                }
              ],
              "body": "{\n  \"success\": false,\n  \"error\": \"Email and password are required\"\n}"
            },
            {
              "name": "Error - Invalid Credentials (401)",
              "originalRequest": {
                "method": "POST",
                "header": [
                  {
                    "key": "Content-Type",
                    "value": "application/json",
                    "type": "text"
                  }
                ],
                "body": {
                  "mode": "raw",
                  "raw": "{\n  \"email\": \"john@example.com\",\n  \"password\": \"WrongPassword123\"\n}"
                },
                "url": {
                  "raw": "{{base_url}}/api/users/auth/login",
                  "host": [
                    "{{base_url}}"
                  ],
                  "path": [
                    "api",
                    "users",
                    "auth",
                    "login"
                  ]
                }
              },
              "status": "Unauthorized",
              "code": 401,
              "header": [
                {
                  "key": "Content-Type",
                  "value": "application/json"
                }
              ],
              "body": "{\n  \"success\": false,\n  \"error\": \"Invalid email or password\"\n}"
            },
            {
              "name": "Error - Email Not Verified (403)",
              "originalRequest": {
                "method": "POST",
                "header": [
                  {
                    "key": "Content-Type",
                    "value": "application/json",
                    "type": "text"
                  }
                ],
                "body": {
                  "mode": "raw",
                  "raw": "{\n  \"email\": \"unverified@example.com\",\n  \"password\": \"SecurePassword123\"\n}"
                },
                "url": {
                  "raw": "{{base_url}}/api/users/auth/login",
                  "host": [
                    "{{base_url}}"
                  ],
                  "path": [
                    "api",
                    "users",
                    "auth",
                    "login"
                  ]
                }
              },
              "status": "Forbidden",
              "code": 403,
              "header": [
                {
                  "key": "Content-Type",
                  "value": "application/json"
                }
              ],
              "body": "{\n  \"success\": false,\n  \"error\": \"Please verify your email before login\"\n}"
            }
          ]
        },
        {
          "name": "Forgot Password - Send OTP",
          "request": {
            "method": "POST",
            "header": [
              {
                "key": "Content-Type",
                "value": "application/json",
                "type": "text"
              }
            ],
            "body": {
              "mode": "raw",
              "raw": "{\n  \"email\": \"john@example.com\"\n}"
            },
            "url": {
              "raw": "{{base_url}}/api/users/auth/forgot-password",
              "host": [
                "{{base_url}}"
              ],
              "path": [
                "api",
                "users",
                "auth",
                "forgot-password"
              ]
            },
            "description": "Send password reset OTP to user's email. Email must be registered and verified."
          },
          "response": [
            {
              "name": "Success Response (200)",
              "originalRequest": {
                "method": "POST",
                "header": [
                  {
                    "key": "Content-Type",
                    "value": "application/json",
                    "type": "text"
                  }
                ],
                "body": {
                  "mode": "raw",
                  "raw": "{\n  \"email\": \"john@example.com\"\n}"
                },
                "url": {
                  "raw": "{{base_url}}/api/users/auth/forgot-password",
                  "host": [
                    "{{base_url}}"
                  ],
                  "path": [
                    "api",
                    "users",
                    "auth",
                    "forgot-password"
                  ]
                }
              },
              "status": "OK",
              "code": 200,
              "header": [
                {
                  "key": "Content-Type",
                  "value": "application/json"
                }
              ],
              "body": "{\n  \"success\": true,\n  \"message\": \"Password reset code sent to your email.\",\n  \"data\": {\n    \"email\": \"john@example.com\"\n  }\n}"
            },
            {
              "name": "Error - Email Not Found (404)",
              "originalRequest": {
                "method": "POST",
                "header": [
                  {
                    "key": "Content-Type",
                    "value": "application/json",
                    "type": "text"
                  }
                ],
                "body": {
                  "mode": "raw",
                  "raw": "{\n  \"email\": \"nonexistent@example.com\"\n}"
                },
                "url": {
                  "raw": "{{base_url}}/api/users/auth/forgot-password",
                  "host": [
                    "{{base_url}}"
                  ],
                  "path": [
                    "api",
                    "users",
                    "auth",
                    "forgot-password"
                  ]
                }
              },
              "status": "Not Found",
              "code": 404,
              "header": [
                {
                  "key": "Content-Type",
                  "value": "application/json"
                }
              ],
              "body": "{\n  \"success\": false,\n  \"error\": \"Email not found\"\n}"
            }
          ]
        },
        {
          "name": "Verify Reset OTP",
          "request": {
            "method": "POST",
            "header": [
              {
                "key": "Content-Type",
                "value": "application/json",
                "type": "text"
              }
            ],
            "body": {
              "mode": "raw",
              "raw": "{\n  \"email\": \"john@example.com\",\n  \"otp\": \"12345\"\n}"
            },
            "url": {
              "raw": "{{base_url}}/api/users/auth/verify-reset-otp",
              "host": [
                "{{base_url}}"
              ],
              "path": [
                "api",
                "users",
                "auth",
                "verify-reset-otp"
              ]
            },
            "description": "Verify the 5-digit OTP code received for password reset."
          },
          "response": [
            {
              "name": "Success Response (200)",
              "originalRequest": {
                "method": "POST",
                "header": [
                  {
                    "key": "Content-Type",
                    "value": "application/json",
                    "type": "text"
                  }
                ],
                "body": {
                  "mode": "raw",
                  "raw": "{\n  \"email\": \"john@example.com\",\n  \"otp\": \"12345\"\n}"
                },
                "url": {
                  "raw": "{{base_url}}/api/users/auth/verify-reset-otp",
                  "host": [
                    "{{base_url}}"
                  ],
                  "path": [
                    "api",
                    "users",
                    "auth",
                    "verify-reset-otp"
                  ]
                }
              },
              "status": "OK",
              "code": 200,
              "header": [
                {
                  "key": "Content-Type",
                  "value": "application/json"
                }
              ],
              "body": "{\n  \"success\": true,\n  \"message\": \"OTP verified successfully. You can now reset your password.\",\n  \"data\": {\n    \"email\": \"john@example.com\",\n    \"userId\": \"550e8400-e29b-41d4-a716-446655440000\"\n  }\n}"
            },
            {
              "name": "Error - Invalid OTP (400)",
              "originalRequest": {
                "method": "POST",
                "header": [
                  {
                    "key": "Content-Type",
                    "value": "application/json",
                    "type": "text"
                  }
                ],
                "body": {
                  "mode": "raw",
                  "raw": "{\n  \"email\": \"john@example.com\",\n  \"otp\": \"99999\"\n}"
                },
                "url": {
                  "raw": "{{base_url}}/api/users/auth/verify-reset-otp",
                  "host": [
                    "{{base_url}}"
                  ],
                  "path": [
                    "api",
                    "users",
                    "auth",
                    "verify-reset-otp"
                  ]
                }
              },
              "status": "Bad Request",
              "code": 400,
              "header": [
                {
                  "key": "Content-Type",
                  "value": "application/json"
                }
              ],
              "body": "{\n  \"success\": false,\n  \"error\": \"Invalid OTP. Please try again.\"\n}"
            },
            {
              "name": "Error - Too Many Attempts (429)",
              "originalRequest": {
                "method": "POST",
                "header": [
                  {
                    "key": "Content-Type",
                    "value": "application/json",
                    "type": "text"
                  }
                ],
                "body": {
                  "mode": "raw",
                  "raw": "{\n  \"email\": \"john@example.com\",\n  \"otp\": \"99999\"\n}"
                },
                "url": {
                  "raw": "{{base_url}}/api/users/auth/verify-reset-otp",
                  "host": [
                    "{{base_url}}"
                  ],
                  "path": [
                    "api",
                    "users",
                    "auth",
                    "verify-reset-otp"
                  ]
                }
              },
              "status": "Too Many Requests",
              "code": 429,
              "header": [
                {
                  "key": "Content-Type",
                  "value": "application/json"
                }
              ],
              "body": "{\n  \"success\": false,\n  \"error\": \"Maximum OTP attempts exceeded. Please request a new password reset code.\"\n}"
            }
          ]
        },
        {
          "name": "Reset Password",
          "request": {
            "method": "POST",
            "header": [
              {
                "key": "Content-Type",
                "value": "application/json",
                "type": "text"
              }
            ],
            "body": {
              "mode": "raw",
              "raw": "{\n  \"email\": \"john@example.com\",\n  \"newPassword\": \"NewSecurePassword123\",\n  \"confirmPassword\": \"NewSecurePassword123\"\n}"
            },
            "url": {
              "raw": "{{base_url}}/api/users/auth/reset-password",
              "host": [
                "{{base_url}}"
              ],
              "path": [
                "api",
                "users",
                "auth",
                "reset-password"
              ]
            },
            "description": "Reset password after OTP verification. Password must be at least 8 characters and both passwords must match. Make sure to verify OTP first via /verify-reset-otp endpoint."
          },
          "response": [
            {
              "name": "Success Response (200)",
              "originalRequest": {
                "method": "POST",
                "header": [
                  {
                    "key": "Content-Type",
                    "value": "application/json",
                    "type": "text"
                  }
                ],
                "body": {
                  "mode": "raw",
                  "raw": "{\n  \"email\": \"john@example.com\",\n  \"newPassword\": \"NewSecurePassword123\",\n  \"confirmPassword\": \"NewSecurePassword123\"\n}"
                },
                "url": {
                  "raw": "{{base_url}}/api/users/auth/reset-password",
                  "host": [
                    "{{base_url}}"
                  ],
                  "path": [
                    "api",
                    "users",
                    "auth",
                    "reset-password"
                  ]
                }
              },
              "status": "OK",
              "code": 200,
              "header": [
                {
                  "key": "Content-Type",
                  "value": "application/json"
                }
              ],
              "body": "{\n  \"success\": true,\n  \"message\": \"Password reset successfully. You can now login with your new password.\",\n  \"data\": {\n    \"email\": \"john@example.com\"\n  }\n}"
            },
            {
              "name": "Error - OTP Not Verified (400)",
              "originalRequest": {
                "method": "POST",
                "header": [
                  {
                    "key": "Content-Type",
                    "value": "application/json",
                    "type": "text"
                  }
                ],
                "body": {
                  "mode": "raw",
                  "raw": "{\n  \"email\": \"john@example.com\",\n  \"newPassword\": \"NewSecurePassword123\",\n  \"confirmPassword\": \"NewSecurePassword123\"\n}"
                },
                "url": {
                  "raw": "{{base_url}}/api/users/auth/reset-password",
                  "host": [
                    "{{base_url}}"
                  ],
                  "path": [
                    "api",
                    "users",
                    "auth",
                    "reset-password"
                  ]
                }
              },
              "status": "Bad Request",
              "code": 400,
              "header": [
                {
                  "key": "Content-Type",
                  "value": "application/json"
                }
              ],
              "body": "{\n  \"success\": false,\n  \"error\": \"Please verify your OTP first before resetting password.\"\n}"
            },
            {
              "name": "Error - Passwords Don't Match (400)",
              "originalRequest": {
                "method": "POST",
                "header": [
                  {
                    "key": "Content-Type",
                    "value": "application/json",
                    "type": "text"
                  }
                ],
                "body": {
                  "mode": "raw",
                  "raw": "{\n  \"email\": \"john@example.com\",\n  \"newPassword\": \"NewSecurePassword123\",\n  \"confirmPassword\": \"DifferentPassword123\"\n}"
                },
                "url": {
                  "raw": "{{base_url}}/api/users/auth/reset-password",
                  "host": [
                    "{{base_url}}"
                  ],
                  "path": [
                    "api",
                    "users",
                    "auth",
                    "reset-password"
                  ]
                }
              },
              "status": "Bad Request",
              "code": 400,
              "header": [
                {
                  "key": "Content-Type",
                  "value": "application/json"
                }
              ],
              "body": "{\n  \"success\": false,\n  \"error\": \"Passwords do not match\"\n}"
            },
            {
              "name": "Error - Password Too Short (400)",
              "originalRequest": {
                "method": "POST",
                "header": [
                  {
                    "key": "Content-Type",
                    "value": "application/json",
                    "type": "text"
                  }
                ],
                "body": {
                  "mode": "raw",
                  "raw": "{\n  \"email\": \"john@example.com\",\n  \"newPassword\": \"short\",\n  \"confirmPassword\": \"short\"\n}"
                },
                "url": {
                  "raw": "{{base_url}}/api/users/auth/reset-password",
                  "host": [
                    "{{base_url}}"
                  ],
                  "path": [
                    "api",
                    "users",
                    "auth",
                    "reset-password"
                  ]
                }
              },
              "status": "Bad Request",
              "code": 400,
              "header": [
                {
                  "key": "Content-Type",
                  "value": "application/json"
                }
              ],
              "body": "{\n  \"success\": false,\n  \"error\": \"Password must be at least 8 characters long\"\n}"
            }
          ]
        }
      ]
    }
  ],
  "variable": [
    {
      "key": "base_url",
      "value": "http://localhost:3000",
      "type": "string"
    }
  ]
}
